faststyle/__init__.py
faststyle/_nbdev.py
faststyle/callback.py
faststyle/core.py
faststyle/data.py
faststyle/layer_features.py
faststyle/learner.py
faststyle/loss.py
faststyle/models.py
faststyle-0.0.4.dist-info/LICENSE
faststyle-0.0.4.dist-info/METADATA
faststyle-0.0.4.dist-info/WHEEL
faststyle-0.0.4.dist-info/entry_points.txt
faststyle-0.0.4.dist-info/top_level.txt
faststyle-0.0.4.dist-info/RECORD
