Metadata-Version: 2.1
Name: faststyle
Version: 0.0.4
Summary: Fast style transfer API
Home-page: https://github.com/lgvaz/faststyle
Author: lgvaz
Author-email: lgvaz42@gmail.com
License: Apache Software License 2.0
Keywords: Fast style transfer
Platform: UNKNOWN
Classifier: Development Status :: 3 - Alpha
Classifier: Intended Audience :: Developers
Classifier: License :: OSI Approved :: Apache Software License
Classifier: Natural Language :: English
Classifier: Programming Language :: Python :: 3.6
Classifier: Programming Language :: Python :: 3.7
Classifier: Programming Language :: Python :: 3.8
Requires-Python: >=3.6
Requires-Dist: fastai (>=2.0.16)
Requires-Dist: fastcore (>=1.2.5)
Requires-Dist: kornia
Requires-Dist: torch (==1.6.0)
Requires-Dist: torchvision (==0.7)
